{
    "feature": {
        "attributes": {
            "OBJECTID": 17,
            "MUKIM": "Bandar Rengit",
            "DAERAH": "Batu Pahat",
            "NEGERI": "Johor"
        },
        "geometry": {
            "rings": [
                [
                    [
                        103.14477455100007,
                        1.678607244000034
                    ],
                    [
                        103.14446807400009,
                        1.6787089260000698
                    ],
                    [
                        103.14431113200004,
                        1.678760900000043
                    ],
                    [
                        103.14478840700008,
                        1.6801457430000255
                    ],
                    [
                        103.14508002900004,
                        1.6803448680000201
                    ],
                    [
                        103.14518633400007,
                        1.6806104220000293
                    ],
                    [
                        103.14561123900006,
                        1.6818402410000317
                    ],
                    [
                        103.14610765500004,
                        1.6816685050000615
                    ],
                    [
                        103.14620354400006,
                        1.6816343410000627
                    ],
                    [
                        103.14678290800003,
                        1.6814279870000632
                    ],
                    [
                        103.14740418000008,
                        1.6812960780000594
                    ],
                    [
                        103.14747997000006,
                        1.681536756000071
                    ],
                    [
                        103.14774729000004,
                        1.6814879780000638
                    ],
                    [
                        103.14785951500005,
                        1.6814674730000547
                    ],
                    [
                        103.14799794400005,
                        1.6814963520000674
                    ],
                    [
                        103.14922562600003,
                        1.6815216630000691
                    ],
                    [
                        103.14943496800004,
                        1.6815259570000762
                    ],
                    [
                        103.15024458500005,
                        1.6815409680000357
                    ],
                    [
                        103.15109027700004,
                        1.681556884000031
                    ],
                    [
                        103.15088915900009,
                        1.6805524100000753
                    ],
                    [
                        103.15077983200007,
                        1.6799989780000715
                    ],
                    [
                        103.15075151800005,
                        1.6797189620000381
                    ],
                    [
                        103.15069583800005,
                        1.679141927000046
                    ],
                    [
                        103.15056492200006,
                        1.6785953620000669
                    ],
                    [
                        103.15046018800007,
                        1.6781589620000545
                    ],
                    [
                        103.15029969400007,
                        1.6774910200000477
                    ],
                    [
                        103.14851979900004,
                        1.677608767000038
                    ],
                    [
                        103.14689651100008,
                        1.6778108220000263
                    ],
                    [
                        103.14674310300006,
                        1.6771652280000353
                    ],
                    [
                        103.14666701500005,
                        1.6768442350000328
                    ],
                    [
                        103.14659001200005,
                        1.6765198060000444
                    ],
                    [
                        103.14651299700006,
                        1.6761952850000625
                    ],
                    [
                        103.14586491600005,
                        1.676302501000066
                    ],
                    [
                        103.14565278900005,
                        1.6763376350000385
                    ],
                    [
                        103.14603325800005,
                        1.6777238220000754
                    ],
                    [
                        103.14471367100003,
                        1.677816415000052
                    ],
                    [
                        103.14496108900005,
                        1.6785454270000741
                    ],
                    [
                        103.14477455100007,
                        1.678607244000034
                    ]
                ]
            ]
        }
    }
}